guillotina_oauth/__init__.py
guillotina_oauth/install.py
guillotina_oauth/interfaces.py
guillotina_oauth/oauth.py
guillotina_oauth/tests/__init__.py
guillotina_oauth/tests/conftest.py
guillotina_oauth/tests/test_setup.py
guillotina_oauth-2.0.0.dist-info/DESCRIPTION.rst
guillotina_oauth-2.0.0.dist-info/METADATA
guillotina_oauth-2.0.0.dist-info/RECORD
guillotina_oauth-2.0.0.dist-info/WHEEL
guillotina_oauth-2.0.0.dist-info/entry_points.txt
guillotina_oauth-2.0.0.dist-info/metadata.json
guillotina_oauth-2.0.0.dist-info/top_level.txt
guillotina_oauth-2.0.0.dist-info/zip-safe
