Metadata-Version: 2.0
Name: guillotina-oauth
Version: 2.0.0
Summary: guillotina oauth support
Home-page: https://pypi.python.org/pypi/guillotina_oauth
Author: Ramon Navarro Bosch
Author-email: ramon@plone.org
License: GPL version 3
Keywords: guillotina oauth
Platform: UNKNOWN
Classifier: Programming Language :: Python :: 3.6
Classifier: Topic :: Software Development :: Libraries :: Python Modules
Requires-Dist: setuptools
Requires-Dist: guillotina (>=4.0.0)
Requires-Dist: ujson
Requires-Dist: pyjwt
Requires-Dist: lru-dict
